setup.py
src/yes24/__init__.py
src/yes24/testyes24.py
src/yes24/util.py
src/yes24/yes24.py
yes24.egg-info/PKG-INFO
yes24.egg-info/SOURCES.txt
yes24.egg-info/dependency_links.txt
yes24.egg-info/requires.txt
yes24.egg-info/top_level.txt