Metadata-Version: 1.0
Name: yes24
Version: 0.1
Summary: yes24.com api
Home-page: https://github.com/dokenzy/yes24-py
Author: dokenzy
Author-email: dokenzy@gmail.com
License: MIT License
Platform: UNKNOWN
